LupSeat-1.3.0.data/scripts/lupseat
models/__init__.py
models/assign.py
models/eval.py
models/fsave.py
models/gui.py
models/parser.py
models/room.py
models/seat.py
models/student.py
LupSeat-1.3.0.dist-info/LICENSE
LupSeat-1.3.0.dist-info/METADATA
LupSeat-1.3.0.dist-info/WHEEL
LupSeat-1.3.0.dist-info/top_level.txt
LupSeat-1.3.0.dist-info/RECORD
