Metadata-Version: 2.1
Name: LupSeat
Version: 1.3.0
Summary: Automatically assigns seats to students in a smart way.
Home-page: UNKNOWN
Author: Hiroya Gojo
Author-email: hiroyagojo@gmail.com
License: UNKNOWN
Platform: UNKNOWN
Classifier: Programming Language :: Python :: 3
Classifier: License :: OSI Approved :: MIT License
Classifier: Operating System :: OS Independent
Requires-Dist: Pillow (>=8.0.1)
Requires-Dist: fpdf (>=1.7.2)
Requires-Dist: papersize (>=1.0.1)
